mmstat/__init__.py
mmstat/version.py
mmstat/github/__init__.py
mmstat/lark/__init__.py
mmstat/webot/__init__.py
mmbi-0.0.1.dist-info/LICENSE
mmbi-0.0.1.dist-info/METADATA
mmbi-0.0.1.dist-info/WHEEL
mmbi-0.0.1.dist-info/top_level.txt
mmbi-0.0.1.dist-info/RECORD
