Metadata-Version: 2.1
Name: mmbi
Version: 0.0.1
Summary: OpenMMLab Stats Engine
Home-page: https://github.com/open-mmlab/mmengine
Author: vansin
Author-email: vansin@aliyun.com
Classifier: Development Status :: 4 - Beta
Classifier: License :: OSI Approved :: Apache Software License
Classifier: Operating System :: OS Independent
Classifier: Programming Language :: Python :: 3
Classifier: Programming Language :: Python :: 3.6
Classifier: Programming Language :: Python :: 3.7
Classifier: Programming Language :: Python :: 3.8
Classifier: Programming Language :: Python :: 3.9
Classifier: Programming Language :: Python :: 3.10
Classifier: Topic :: Utilities
Requires-Python: >=3.6
License-File: LICENSE
